hivemind_mic_sat/__init__.py
hivemind_mic_sat/version.py
hivemind_mic_sat/res/snd/acknowledge.mp3
hivemind_mic_sat/res/snd/error.mp3
hivemind_mic_sat/res/snd/start_listening.wav
hivemind_mic_satellite-0.7.1.dist-info/METADATA
hivemind_mic_satellite-0.7.1.dist-info/WHEEL
hivemind_mic_satellite-0.7.1.dist-info/entry_points.txt
hivemind_mic_satellite-0.7.1.dist-info/top_level.txt
hivemind_mic_satellite-0.7.1.dist-info/RECORD
