Metadata-Version: 2.1
Name: hivemind-mic-satellite
Version: 0.7.1
Summary: Remote microphone for HiveMind
Home-page: https://github.com/JarbasHiveMind/hivemind-mic-satellite
Author: jarbasAI
Author-email: jarbasai@mailfence.com
License: Apache2.0
Requires-Dist: hivemind-bus-client<1.0.0,>=0.1.0
Requires-Dist: ovos-plugin-manager<1.0.0
Requires-Dist: ovos-audio<1.0.0
Requires-Dist: click
Requires-Dist: pybase64
